syrenka/__init__.py
syrenka/__main__.py
syrenka/base.py
syrenka/classdiagram.py
syrenka/flowchart.py
syrenka/generate.py
syrenka/lang/__init__.py
syrenka/lang/base.py
syrenka/lang/python.py
syrenka-0.5.6.dist-info/METADATA
syrenka-0.5.6.dist-info/WHEEL
syrenka-0.5.6.dist-info/licenses/LICENSE
syrenka-0.5.6.dist-info/RECORD
