Metadata-Version: 2.4
Name: syrenka
Version: 0.5.6
Summary: easily create mermaid diagrams with python, generate class diagrams from python ast, more languages support coming
Project-URL: Homepage, https://github.com/bartlomiejcieszkowski/syrenka
Project-URL: Bug Tracker, https://github.com/bartlomiejcieszkowski/syrenka/issues
Author-email: Bartlomiej Cieszkowski <bartlomiej.cieszkowski@gmail.com>
License: MIT License
License-File: LICENSE
Keywords: markdown,mermaid,mermaid.js
Classifier: License :: OSI Approved :: MIT License
Classifier: Programming Language :: Python :: 3
Requires-Python: >=3.9.16
Requires-Dist: strenum>=0.4.15; python_version < '3.11'
